server/__init__.py
server/add.py
sixthirty-0.0.1.dist-info/LICENSE
sixthirty-0.0.1.dist-info/METADATA
sixthirty-0.0.1.dist-info/WHEEL
sixthirty-0.0.1.dist-info/entry_points.txt
sixthirty-0.0.1.dist-info/top_level.txt
sixthirty-0.0.1.dist-info/RECORD
