Metadata-Version: 2.1
Name: sixthirty
Version: 0.0.1
Summary: Monorepo of 6-30 services
Home-page: https://github.com/dvcorreia/6-30
Author: Diogo Correia
Author-email: dv_correia@hotmail.com
License: UNKNOWN
Project-URL: Bug Reports, https://github.com/dvcorreia/6-30/issues
Project-URL: Source, https://github.com/dvcorreia/6-30
Keywords: beer,manage,count,metrics
Platform: UNKNOWN
Classifier: Development Status :: 3 - Alpha
Classifier: License :: OSI Approved :: MIT License
Classifier: Programming Language :: Python :: 3.8
Classifier: Programming Language :: Python :: 3.9
Classifier: Programming Language :: Python :: 3.10
Requires-Python: >=3.8, <4
License-File: LICENSE
Provides-Extra: dev
Provides-Extra: test
